odoo9_addon_pos_transfer_account-9.0.1.0.0.99.dev6-py3.6-nspkg.pth
odoo_addons/pos_transfer_account/README.rst
odoo_addons/pos_transfer_account/__init__.py
odoo_addons/pos_transfer_account/__openerp__.py
odoo_addons/pos_transfer_account/demo/account_account.xml
odoo_addons/pos_transfer_account/demo/pos_config.xml
odoo_addons/pos_transfer_account/i18n/ca.po
odoo_addons/pos_transfer_account/i18n/es.po
odoo_addons/pos_transfer_account/i18n/fr.po
odoo_addons/pos_transfer_account/i18n/pos_transfer_account.pot
odoo_addons/pos_transfer_account/models/__init__.py
odoo_addons/pos_transfer_account/models/cash_box_in.py
odoo_addons/pos_transfer_account/models/cash_box_out.py
odoo_addons/pos_transfer_account/models/pos_config.py
odoo_addons/pos_transfer_account/static/description/icon.png
odoo_addons/pos_transfer_account/static/description/pos_config.png
odoo_addons/pos_transfer_account/views/view_pos_config.xml
odoo9_addon_pos_transfer_account-9.0.1.0.0.99.dev6.dist-info/METADATA
odoo9_addon_pos_transfer_account-9.0.1.0.0.99.dev6.dist-info/WHEEL
odoo9_addon_pos_transfer_account-9.0.1.0.0.99.dev6.dist-info/namespace_packages.txt
odoo9_addon_pos_transfer_account-9.0.1.0.0.99.dev6.dist-info/top_level.txt
odoo9_addon_pos_transfer_account-9.0.1.0.0.99.dev6.dist-info/RECORD
