Metadata-Version: 2.1
Name: odoo9-addon-pos-transfer-account
Version: 9.0.1.0.0.99.dev6
Summary: Point of Sale - Transfer Account
Home-page: http://www.lalouve.net
Author: La Louve, Odoo Community Association (OCA)
Author-email: support@odoo-community.org
License: UNKNOWN
Platform: UNKNOWN
Classifier: Programming Language :: Python
Classifier: Framework :: Odoo
Requires-Python: ~=2.7
Requires-Dist: odoo (<9.1a,>=9.0a)
